{
  "$schema": "https://developer.microsoft.com/json-schemas/fabric/item/report/definition/visualContainer/2.5.0/schema.json",
  "name": "kpicard001medallas",
  "position": { "x": 0, "y": 35, "z": 0, "height": 72, "width": 255, "tabOrder": 1 },
  "visual": {
    "visualType": "card",
    "query": {
      "queryState": {
        "Values": {
          "projections": [
            {
              "field": {
                "Measure": {
                  "Expression": { "SourceRef": { "Entity": "FACT_MEDALLA" } },
                  "Property": "Total Medallas"
                }
              },
              "queryRef": "FACT_MEDALLA.Total Medallas",
              "active": true
            }
          ]
        }
      }
    }
  }
}
